[
    {
        "image_id": 0,
        "category_id": 12,
        "bbox": [
            259.7555847167969,
            139.60809326171875,
            353.7318420410156,
            216.5086669921875
        ],
        "score": 1
    },
    {
        "image_id": 0,
        "category_id": 13,
        "bbox": [
            283.6335144042969,
            355.3195495605469,
            336.4677429199219,
            219.85745239257812
        ],
        "score": 1
    },
    {
        "image_id": 0,
        "category_id": 11,
        "bbox": [
            272.06451416015625,
            6.614258766174316,
            330.0699462890625,
            126.08312892913818
        ],
        "score": 1
    }
]